solidbyte/__init__.py
solidbyte/accounts/__init__.py
solidbyte/bin/solc
solidbyte/cli/__init__.py
solidbyte/cli/accounts.py
solidbyte/cli/compile.py
solidbyte/cli/console.py
solidbyte/cli/deploy.py
solidbyte/cli/handler.py
solidbyte/cli/init.py
solidbyte/cli/show.py
solidbyte/cli/test.py
solidbyte/cli/version.py
solidbyte/common/__init__.py
solidbyte/common/exceptions.py
solidbyte/common/logging.py
solidbyte/common/metafile.py
solidbyte/common/web3.py
solidbyte/compile/__init__.py
solidbyte/compile/compiler.py
solidbyte/console/__init__.py
solidbyte/deploy/__init__.py
solidbyte/deploy/objects.py
solidbyte/templates/__init__.py
solidbyte/templates/template.py
solidbyte/templates/templates/__init__.py
solidbyte/templates/templates/bare/__init__.py
solidbyte/templates/templates/bare/networks.yml
solidbyte/templates/templates/bare/deploy/__init__.py
solidbyte/templates/templates/bare/deploy/deploy_main.py
solidbyte/templates/templates/erc20/__init__.py
solidbyte/templates/templates/erc20/networks.yml
solidbyte/templates/templates/erc20/contracts/ERC20.sol
solidbyte/templates/templates/erc20/contracts/IERC20.sol
solidbyte/templates/templates/erc20/contracts/SafeMath.sol
solidbyte/templates/templates/erc20/deploy/__init__.py
solidbyte/templates/templates/erc20/deploy/deploy_main.py
solidbyte/templates/templates/erc20/tests/test_erc20.py
solidbyte/testing/__init__.py
solidbyte-0.0.3a1.dist-info/LICENSE
solidbyte-0.0.3a1.dist-info/METADATA
solidbyte-0.0.3a1.dist-info/WHEEL
solidbyte-0.0.3a1.dist-info/entry_points.txt
solidbyte-0.0.3a1.dist-info/top_level.txt
solidbyte-0.0.3a1.dist-info/RECORD
