Metadata-Version: 2.1
Name: solidbyte
Version: 0.0.3a1
Summary: Solidity development tools for creating Ethereum smart contracts
Home-page: https://github.com/mikeshultz/solidbyte
Author: Mike Shultz
Author-email: mike@gointo.software
License: UNKNOWN
Keywords: solidity ethereum development
Platform: UNKNOWN
Classifier: Development Status :: 3 - Alpha
Classifier: Intended Audience :: Developers
Classifier: Topic :: Software Development :: Build Tools
Classifier: License :: OSI Approved :: GNU General Public License v3 or later (GPLv3+)
Classifier: Programming Language :: Python :: 3
Classifier: Programming Language :: Python :: 3.4
Classifier: Programming Language :: Python :: 3.5
Classifier: Programming Language :: Python :: 3.6
Requires-Dist: pytest (~=3.9.3)
Requires-Dist: eth-account (==0.3.0)
Requires-Dist: web3 (==4.7.2)
Requires-Dist: pyyaml (==3.13)
Provides-Extra: dev
Requires-Dist: twine (~=1.12.1); extra == 'dev'
Requires-Dist: setuptools (~=40.5.0); extra == 'dev'
Requires-Dist: wheel (~=0.32.2); extra == 'dev'
Provides-Extra: test
